py_tes-1.1.2.dist-info/licenses/LICENSE
tes/__init__.py
tes/client.py
tes/models.py
tes/utils.py
py_tes-1.1.2.dist-info/METADATA
py_tes-1.1.2.dist-info/WHEEL
py_tes-1.1.2.dist-info/top_level.txt
py_tes-1.1.2.dist-info/zip-safe
py_tes-1.1.2.dist-info/RECORD
