Metadata-Version: 2.4
Name: py-tes
Version: 1.1.2
Summary: Library for communicating with the GA4GH Task Execution API
Home-page: https://github.com/ohsu-comp-bio/py-tes
Author: OHSU Computational Biology
Author-email: CompBio@ohsu.edu
Maintainer: Kyle Ellrott
Maintainer-email: kellrott@gmail.com
License: MIT
Classifier: Development Status :: 4 - Beta
Classifier: Intended Audience :: Developers
Classifier: Natural Language :: English
Classifier: License :: OSI Approved :: MIT License
Classifier: Topic :: Software Development :: Libraries
Classifier: Programming Language :: Python :: 3
Classifier: Programming Language :: Python :: 3.7
Classifier: Programming Language :: Python :: 3.8
Classifier: Programming Language :: Python :: 3.9
Classifier: Programming Language :: Python :: 3.10
Classifier: Programming Language :: Python :: 3.11
Requires-Python: >=3.7, <4
License-File: LICENSE
Requires-Dist: attrs>=17.4.0
Requires-Dist: python-dateutil>=2.6.1
Requires-Dist: requests>=2.18.2
Requires-Dist: sphinx_rtd_theme
Dynamic: author
Dynamic: author-email
Dynamic: classifier
Dynamic: description
Dynamic: description-content-type
Dynamic: home-page
Dynamic: license
Dynamic: license-file
Dynamic: maintainer
Dynamic: maintainer-email
Dynamic: requires-dist
Dynamic: requires-python
Dynamic: summary
